chisel_nbdev/__init__.py
chisel_nbdev/_nbdev.py
chisel_nbdev/clean_scala.py
chisel_nbdev/cli.py
chisel_nbdev/export_scala.py
chisel_nbdev/export_scala2html.py
chisel_nbdev/merge.py
chisel_nbdev/showdoc.py
chisel_nbdev/sync_scala.py
chisel_nbdev/test_scala.py
chisel_nbdev/templates/autogen.tpl
chisel_nbdev/templates/hide-md.tpl
chisel_nbdev/templates/hide.tpl
chisel_nbdev/templates/jekyll-md.tpl
chisel_nbdev/templates/jekyll.tpl
chisel_nbdev/templates/md.tpl
chisel_nbdev-0.1.5.dist-info/LICENSE
chisel_nbdev-0.1.5.dist-info/METADATA
chisel_nbdev-0.1.5.dist-info/WHEEL
chisel_nbdev-0.1.5.dist-info/entry_points.txt
chisel_nbdev-0.1.5.dist-info/top_level.txt
chisel_nbdev-0.1.5.dist-info/RECORD
