Metadata-Version: 2.1
Name: chisel-nbdev
Version: 0.1.5
Summary: Port of nbdev to write SCALA / chisel library entirely in notebooks
Home-page: https://github.com/ucsc-vama/chisel_nbdev
Author: JasonVranek
Author-email: jvranek@ucsc.edu
License: Apache Software License 2.0
Keywords: jupyter notebook / chisel / scala
Platform: UNKNOWN
Classifier: Development Status :: 5 - Production/Stable
Classifier: Intended Audience :: Developers
Classifier: License :: OSI Approved :: Apache Software License
Classifier: Natural Language :: English
Classifier: Programming Language :: Python :: 3.6
Classifier: Programming Language :: Python :: 3.7
Classifier: Programming Language :: Python :: 3.8
Requires-Python: >=3.6
Requires-Dist: pip
Requires-Dist: packaging
Requires-Dist: fastcore (>=1.3.1)
Requires-Dist: nbformat (>=4.4.0)
Requires-Dist: nbconvert (<6)
Requires-Dist: pyyaml
Requires-Dist: jupyter-client
Requires-Dist: jupyter
Requires-Dist: ipykernel
Requires-Dist: nbdev
Provides-Extra: dev
